[
{
    "model": "appointment.slot",
    "pk": 1,
    "fields": {
        "created_at": "2023-04-19T05:06:49.805Z",
        "updated_at": "2023-04-19T05:06:49.805Z",
        "time": "12:00 PM - 01:00 PM",
        "is_active": true
    }
},
{
    "model": "appointment.slot",
    "pk": 2,
    "fields": {
        "created_at": "2023-04-19T05:10:33.960Z",
        "updated_at": "2023-04-19T05:10:33.960Z",
        "time": "01:00 PM - 02:00 PM",
        "is_active": true
    }
},
{
    "model": "appointment.slot",
    "pk": 3,
    "fields": {
        "created_at": "2023-04-19T05:10:47.315Z",
        "updated_at": "2023-04-19T05:11:12.270Z",
        "time": "02:00 PM - 03:00 PM",
        "is_active": true
    }
},
{
    "model": "appointment.slot",
    "pk": 4,
    "fields": {
        "created_at": "2023-04-19T05:11:05.397Z",
        "updated_at": "2023-04-19T05:11:05.397Z",
        "time": "03:00 PM - 04:00 PM",
        "is_active": true
    }
},
{
    "model": "appointment.bookappointment",
    "pk": 1,
    "fields": {
        "created_at": "2023-04-19T05:19:40.519Z",
        "updated_at": "2023-04-19T05:19:40.519Z",
        "name": "kumar",
        "email": "sam@gmail.com",
        "phone_number": "9444412345",
        "date": "2023-01-01",
        "time": 4,
        "store": 1,
        "product": 1,
        "booking_type": "PRODUCT",
        "service": []
    }
},
{
    "model": "appointment.bookappointment",
    "pk": 3,
    "fields": {
        "created_at": "2023-04-19T05:37:03.550Z",
        "updated_at": "2023-04-19T05:37:03.550Z",
        "name": "James",
        "email": "sam@gmail.com",
        "phone_number": "9443312345",
        "date": "2023-01-01",
        "time": 4,
        "store": 1,
        "product": null,
        "booking_type": "SERVICES",
        "service": []
    }
},
{
    "model": "appointment.bookappointment",
    "pk": 4,
    "fields": {
        "created_at": "2023-04-19T05:38:15.429Z",
        "updated_at": "2023-04-19T05:38:15.429Z",
        "name": "James",
        "email": "sam@gmail.com",
        "phone_number": "9443312345",
        "date": "2023-01-01",
        "time": 4,
        "store": 1,
        "product": null,
        "booking_type": "SERVICES",
        "service": [
            1,
            2
        ]
    }
},
{
    "model": "appointment.bookappointment",
    "pk": 5,
    "fields": {
        "created_at": "2023-04-19T05:41:37.795Z",
        "updated_at": "2023-04-19T05:41:37.795Z",
        "name": "James",
        "email": "sam@gmail.com",
        "phone_number": "9443312345",
        "date": "2023-01-01",
        "time": 4,
        "store": 1,
        "product": null,
        "booking_type": "SERVICES",
        "service": [
            1,
            2
        ]
    }
},
{
    "model": "appointment.bookappointment",
    "pk": 6,
    "fields": {
        "created_at": "2023-04-19T06:06:56.701Z",
        "updated_at": "2023-04-19T06:06:56.701Z",
        "name": "James",
        "email": "sam@gmail.com",
        "phone_number": "9443312345",
        "date": "2023-01-01",
        "time": 4,
        "store": 1,
        "product": null,
        "booking_type": "SERVICES",
        "service": [
            1,
            2
        ]
    }
},
{
    "model": "appointment.bookappointment",
    "pk": 7,
    "fields": {
        "created_at": "2023-04-19T06:11:01.176Z",
        "updated_at": "2023-04-19T06:11:01.176Z",
        "name": "James",
        "email": "sam@gmail.com",
        "phone_number": "9443312345",
        "date": "2023-01-01",
        "time": 4,
        "store": 1,
        "product": null,
        "booking_type": "SERVICE",
        "service": [
            1,
            2
        ]
    }
}
]
